neuralsalience/__init__.py
neuralsalience/attention.py
neuralsalience-0.0.1.dist-info/METADATA
neuralsalience-0.0.1.dist-info/WHEEL
neuralsalience-0.0.1.dist-info/top_level.txt
neuralsalience-0.0.1.dist-info/RECORD
