Metadata-Version: 2.1
Name: neuralsalience
Version: 0.0.1
Summary: Embeddings ponderation scheme, freely adapted from the paper : 'Learning Neural Word Salience Scores' https://arxiv.org/pdf/1709.01186.pdf
Home-page: https://github.com/kerighan/neuralsalience
Author: Maixent Chenebaux
Author-email: max.chbx@gmail.com
License: UNKNOWN
Platform: UNKNOWN
Classifier: Programming Language :: Python :: 3
Classifier: Programming Language :: Python :: 3.7
Classifier: License :: OSI Approved :: MIT License
Classifier: Operating System :: OS Independent
Requires-Python: >=3.5
Requires-Dist: keras
Requires-Dist: numpy
